{
  "posts": [
    {
      "id": 1,
      "title": "Premier post",
      "content": "Contenu du post"
    },
    {
      "id": 2,
      "title": "Un autre post",
      "content": "Contenu du post numéro 2"
    },
    {
      "title": "ddzadzad",
      "content": "vsd vsdvsdvsd",
      "id": 3
    },
    {
      "title": "dzjiodjziodjaz",
      "content": "jfdeiofjeziojfoezijfo",
      "id": 4
    },
    {
      "title": "dza dzad azd",
      "content": "d zadza dzad dad",
      "id": 5
    },
    {
      "title": "fjeiofjieozj",
      "content": "fjeizojfiezojfiezjfoi jfieoz jfioezjfioezjfozj",
      "id": 6
    }
  ]
}